odstr/__init__.py
odstr/btree.py
odstr/odsbtree.py
test/__init__.py
test/innoDB.py
test/test.py
odsbtree-0.1.0.dist-info/LICENSE
odsbtree-0.1.0.dist-info/METADATA
odsbtree-0.1.0.dist-info/WHEEL
odsbtree-0.1.0.dist-info/top_level.txt
odsbtree-0.1.0.dist-info/RECORD
