Metadata-Version: 2.1
Name: odsbtree
Version: 0.1.0
Summary: An efficient binary search tree implementation
Home-page: UNKNOWN
Author: hgs
Author-email: 2523310240@qq.com
License: UNKNOWN
Platform: UNKNOWN
Classifier: Programming Language :: Python :: 3
Classifier: License :: OSI Approved :: MIT License
Classifier: Operating System :: OS Independent
Requires-Python: >=3.6
License-File: LICENSE
